{
  "collections": {
    "business_commands": {
      "additionalProperties": true,
      "primaryKey": "id",
      "properties": {
        "client_context": {
          "additionalProperties": true,
          "type": "object"
        },
        "command_id": {
          "type": "string"
        },
        "command_type": {
          "type": "string"
        },
        "id": {
          "maxLength": 128,
          "type": "string"
        },
        "inbound_channel": {
          "type": "string"
        },
        "module": {
          "type": "string"
        },
        "payload": {
          "additionalProperties": true,
          "type": "object"
        },
        "record_id": {
          "type": "string"
        },
        "status": {
          "type": "string"
        },
        "updated_at_ms": {
          "type": "number"
        }
      },
      "required": [
        "id",
        "command_id",
        "module",
        "command_type",
        "status",
        "updated_at_ms"
      ],
      "type": "object",
      "version": 1
    },
    "spreadsheet_blob_chunks": {
      "additionalProperties": false,
      "primaryKey": "id",
      "properties": {
        "blob_id": {
          "type": "string"
        },
        "created_at_ms": {
          "type": "number"
        },
        "data": {
          "type": "string"
        },
        "encoding": {
          "type": "string"
        },
        "id": {
          "maxLength": 180,
          "type": "string"
        },
        "idx": {
          "type": "number"
        },
        "mime_type": {
          "type": "string"
        },
        "spreadsheet_id": {
          "type": "string"
        },
        "total": {
          "type": "number"
        },
        "version_id": {
          "type": "string"
        }
      },
      "required": [
        "id",
        "blob_id",
        "spreadsheet_id",
        "version_id",
        "idx",
        "total",
        "mime_type",
        "encoding",
        "data",
        "created_at_ms"
      ],
      "type": "object",
      "version": 0
    },
    "spreadsheet_runbooks": {
      "additionalProperties": true,
      "indexes": [
        "title"
      ],
      "primaryKey": "id",
      "properties": {
        "command_type": {
          "type": "string"
        },
        "created_at_ms": {
          "type": "number"
        },
        "description": {
          "type": "string"
        },
        "document_type": {
          "type": "string"
        },
        "id": {
          "maxLength": 160,
          "type": "string"
        },
        "prompt_template": {
          "type": "string"
        },
        "title": {
          "type": "string"
        },
        "updated_at_ms": {
          "type": "number"
        }
      },
      "required": [
        "id",
        "document_type",
        "title",
        "command_type",
        "prompt_template",
        "created_at_ms",
        "updated_at_ms"
      ],
      "type": "object",
      "version": 0
    },
    "spreadsheet_versions": {
      "additionalProperties": true,
      "primaryKey": "id",
      "properties": {
        "blob_id": {
          "type": "string"
        },
        "created_at_ms": {
          "type": "number"
        },
        "diagnostics": {
          "items": {
            "additionalProperties": true,
            "type": "object"
          },
          "type": "array"
        },
        "id": {
          "maxLength": 160,
          "type": "string"
        },
        "model_json": {
          "additionalProperties": true,
          "type": "object"
        },
        "source_kind": {
          "type": "string"
        },
        "spreadsheet_id": {
          "type": "string"
        },
        "updated_at_ms": {
          "type": "number"
        },
        "version": {
          "type": "number"
        }
      },
      "required": [
        "id",
        "spreadsheet_id",
        "version",
        "source_kind",
        "blob_id",
        "model_json",
        "diagnostics",
        "created_at_ms",
        "updated_at_ms"
      ],
      "type": "object",
      "version": 0
    },
    "spreadsheets": {
      "additionalProperties": true,
      "indexes": [
        [
          "is_deleted",
          "updated_at_ms"
        ],
        "updated_at_ms"
      ],
      "primaryKey": "id",
      "properties": {
        "col_count": {
          "type": "number"
        },
        "created_at_ms": {
          "type": "number"
        },
        "current_version_id": {
          "type": "string"
        },
        "diagnostics_count": {
          "type": "number"
        },
        "display_cache": {
          "additionalProperties": true,
          "type": "object"
        },
        "filename": {
          "type": "string"
        },
        "id": {
          "maxLength": 128,
          "type": "string"
        },
        "index_text": {
          "type": "string"
        },
        "is_deleted": {
          "type": "boolean"
        },
        "linked_records": {
          "items": {
            "additionalProperties": true,
            "type": "object"
          },
          "type": "array"
        },
        "mime_type": {
          "type": "string"
        },
        "owner_id": {
          "type": "string"
        },
        "row_count": {
          "type": "number"
        },
        "source_sha256": {
          "type": "string"
        },
        "spreadsheet_type": {
          "type": "string"
        },
        "status": {
          "type": "string"
        },
        "title": {
          "type": "string"
        },
        "updated_at_ms": {
          "type": "number"
        }
      },
      "required": [
        "id",
        "title",
        "filename",
        "mime_type",
        "status",
        "current_version_id",
        "index_text",
        "is_deleted",
        "created_at_ms",
        "updated_at_ms"
      ],
      "type": "object",
      "version": 0
    }
  },
  "migration_strategies": {
    "business_commands": {
      "1": {
        "operations": [
          {
            "default": "",
            "field": "inbound_channel",
            "op": "set_from_first_truthy",
            "paths": [
              "inbound_channel",
              "module"
            ]
          }
        ]
      }
    }
  },
  "module_id": "spreadsheets",
  "schema_format": "ctox-business-os-module-collections-v1"
}
